channels_presence/__init__.py
channels_presence/admin.py
channels_presence/apps.py
channels_presence/decorators.py
channels_presence/models.py
channels_presence/signals.py
channels_presence/tests.py
channels_presence/views.py
channels_presence/management/__init__.py
channels_presence/management/commands/__init__.py
channels_presence/management/commands/prune_presences.py
channels_presence/management/commands/prune_rooms.py
channels_presence/migrations/0001_initial.py
channels_presence/migrations/0002_alter_presence_constraints.py
channels_presence/migrations/__init__.py
django_channels_more_than_present-2.0.1.dist-info/licenses/LICENSE
django_channels_more_than_present-2.0.1.dist-info/METADATA
django_channels_more_than_present-2.0.1.dist-info/WHEEL
django_channels_more_than_present-2.0.1.dist-info/top_level.txt
django_channels_more_than_present-2.0.1.dist-info/RECORD
