Metadata-Version: 2.4
Name: django-channels-more-than-present
Version: 2.0.1
Summary: Tracking socket presence in rooms using django-channels
Home-page: https://github.com/tanrax/django-channels-more-than-present.git
Author: Charlie DeTar
Author-email: Charlie DeTar <cfd@media.mit.edu>
Maintainer: Andros Fenollosa (tanrax)
Maintainer-email: Andros Fenollosa <andros@fenollosa.email>
License: MIT License
Project-URL: Homepage, https://github.com/tanrax/django-channels-more-than-present
Project-URL: Repository, https://github.com/tanrax/django-channels-more-than-present.git
Classifier: Environment :: Web Environment
Classifier: Framework :: Django
Classifier: Framework :: Django :: 3.2
Classifier: Framework :: Django :: 4.0
Classifier: Framework :: Django :: 4.1
Classifier: Framework :: Django :: 4.2
Classifier: Framework :: Django :: 5.0
Classifier: Framework :: Django :: 6.0
Classifier: Intended Audience :: Developers
Classifier: License :: OSI Approved :: MIT License
Classifier: Operating System :: OS Independent
Classifier: Programming Language :: Python
Classifier: Programming Language :: Python :: 3
Classifier: Programming Language :: Python :: 3.8
Classifier: Programming Language :: Python :: 3.9
Classifier: Programming Language :: Python :: 3.10
Classifier: Programming Language :: Python :: 3.11
Classifier: Programming Language :: Python :: 3.12
Classifier: Topic :: Internet :: WWW/HTTP
Classifier: Topic :: Internet :: WWW/HTTP :: Dynamic Content
Requires-Python: >=3.8
License-File: LICENSE
Requires-Dist: Django>=3.2
Requires-Dist: channels>=4.0
Dynamic: author
Dynamic: home-page
Dynamic: license-file
Dynamic: maintainer
Dynamic: requires-python
